cioblender/VERSION
cioblender/__init__.py
cioblender/assets.py
cioblender/buttoned_scroll_panel.py
cioblender/conductor_submitter_plugin.py
cioblender/const.py
cioblender/controller.py
cioblender/driver.py
cioblender/environment.py
cioblender/frames.py
cioblender/instances.py
cioblender/job_title.py
cioblender/json_viewer.py
cioblender/miscellaneous.py
cioblender/notice_grp.py
cioblender/payload.py
cioblender/post_install.py
cioblender/pre_install.py
cioblender/progress_tab.py
cioblender/project.py
cioblender/response_tab.py
cioblender/software.py
cioblender/submission_dialog.py
cioblender/submit.py
cioblender/task.py
cioblender/util.py
cioblender/validation.py
cioblender/validation_tab.py
cioblender/components/__init__.py
cioblender/components/buttoned_scroll_panel.py
cioblender/components/notice_grp.py
cioblender/icons/ConductorConnect_18x18.png
cioblender/icons/ConductorConnect_24x24.png
cioblender/icons/ConductorConnect_30x30.png
cioblender/icons/ConductorConnect_36x36.png
cioblender/icons/ConductorError_18x18.png
cioblender/icons/ConductorError_24x24.png
cioblender/icons/ConductorError_30x30.png
cioblender/icons/ConductorError_36x36.png
cioblender/icons/ConductorHelp_18x18.png
cioblender/icons/ConductorHelp_24x24.png
cioblender/icons/ConductorHelp_30x30.png
cioblender/icons/ConductorHelp_36x36.png
cioblender/icons/ConductorInfo_18x18.png
cioblender/icons/ConductorInfo_24x24.png
cioblender/icons/ConductorInfo_30x30.png
cioblender/icons/ConductorInfo_36x36.png
cioblender/icons/ConductorShow_18x18.png
cioblender/icons/ConductorShow_24x24.png
cioblender/icons/ConductorShow_30x30.png
cioblender/icons/ConductorShow_36x36.png
cioblender/icons/ConductorSubmit_18x18.png
cioblender/icons/ConductorSubmit_24x24.png
cioblender/icons/ConductorSubmit_30x30.png
cioblender/icons/ConductorSubmit_36x36.png
cioblender/icons/ConductorWarning_18x18.png
cioblender/icons/ConductorWarning_24x24.png
cioblender/icons/ConductorWarning_30x30.png
cioblender/icons/ConductorWarning_36x36.png
cioblender-0.3.14.dist-info/METADATA
cioblender-0.3.14.dist-info/WHEEL
cioblender-0.3.14.dist-info/top_level.txt
cioblender-0.3.14.dist-info/RECORD
