Metadata-Version: 2.1
Name: cioblender
Version: 0.3.14
Summary: Blender plugin for Conductor Cloud Rendering Platform.
Home-page: https://github.com/ConductorTechnologies/cioblender
Author: conductor
Author-email: info@conductortech.com
Classifier: Operating System :: OS Independent
Classifier: Programming Language :: Python
Classifier: Topic :: Multimedia :: Graphics :: 3D Rendering
Requires-Dist: ciocore==8.2.0-beta.2
Requires-Dist: ciopath<2.0.0,>=1.1.0
Requires-Dist: cioseq<1.0.0,>=0.5.1
Requires-Dist: json-stream<3.0.0,>=2.3.2
Requires-Dist: PySide6<=6.7.0,>=6.0.0
